{
    "services": {
        "frontend": {
            "image": "ghcr.io/nationalarchives/ds-frontend",
            "version": "26.04.16.1630",
            "repo": "https://github.com/nationalarchives/ds-frontend"
        },
        "wagtail": {
            "image": "ghcr.io/nationalarchives/ds-wagtail",
            "version": "26.04.23.1571",
            "repo": "https://github.com/nationalarchives/ds-wagtail"
        },
        "wagtaildocs": {
            "image": "ghcr.io/nationalarchives/ds-frontend",
            "version": "26.04.16.1630",
            "repo": "https://github.com/nationalarchives/ds-frontend"
        },
        "catalogue": {
            "image": "ghcr.io/nationalarchives/ds-catalogue",
            "version": "26.04.17.2178",
            "repo": "https://github.com/nationalarchives/ds-catalogue"
        },
        "enrichment": {
            "image": "ghcr.io/nationalarchives/ds-frontend-enrichment",
            "version": "26.04.21.108",
            "repo": "https://github.com/nationalarchives/ds-frontend-enrichment"
        },
        "search": {
            "image": "ghcr.io/nationalarchives/ds-sitemap-search",
            "version": "26.04.13.146",
            "repo": "https://github.com/nationalarchives/ds-sitemap-search"
        },
        "feedback": {
            "image": "ghcr.io/nationalarchives/ds-feedback",
            "version": "26.04.17.556",
            "repo": "https://github.com/nationalarchives/ds-feedback"
        },
        "requestservicerecord": {
            "image": "ghcr.io/nationalarchives/ds-request-service-record",
            "version": "26.04.23.727",
            "repo": "https://github.com/nationalarchives/ds-request-service-record"
        },
        "forms": {
            "image": "ghcr.io/nationalarchives/ds-forms",
            "version": "26.04.21.105",
            "repo": "https://github.com/nationalarchives/ds-forms"
        }
    }
}
